{"objects":[{"rotation":0,"offsetY":0,"offsetR":0,"baseDim":{"y":600,"x":800},"allowRotation":true,"userData":"","drawAsTexture":false,"cls":"ZEngine::ZObj","body":{"type":"DYNAMIC","shapes":[{"localVerts":[{"y":-300,"x":-400},{"y":-300,"x":400},{"y":300,"x":400},{"y":300,"x":-400}],"type":"POLYGON","localCOM":{"y":0,"x":0}}]},"scaleX":1,"scaleY":1,"isClip":false,"fps":30,"elasticity":0,"id":"","autoPlay":false,"density":1,"frictionStatic":2,"actions":[],"frictionRolling":0.001,"friction":1,"layer":-2,"x":400,"y":300,"clip":null,"offsetX":0,"isSensor":false},{"drawAsTexture":false,"offsetR":0,"hover":"false","allowRotation":true,"userData":"","rotation":0,"cls":"CButton","baseDim":{"y":70,"x":127},"body":null,"fontFamily":"dedgamecaps","scaleX":1.7,"scaleY":1.7,"isClip":false,"align":"center","fps":30,"id":"bweap","autoPlay":false,"actions":[],"text":"ОРУЖИЕ","layer":3,"fontSize":"30","x":203,"y":573,"clip":"guiatlas.png.shop marker","offsetX":0,"offsetY":0,"tint":"0xffffff"},{"drawAsTexture":false,"offsetR":0,"hover":"false","allowRotation":true,"userData":"","rotation":0,"cls":"CButton","baseDim":{"y":70,"x":127},"body":null,"fontFamily":"dedgamecaps","scaleX":1.7,"scaleY":1.7,"isClip":false,"align":"center","fps":30,"id":"bcloth","autoPlay":false,"actions":[],"text":"ОДЕЖДА","layer":3,"fontSize":"30","x":337,"y":573,"clip":"guiatlas.png.shop marker","offsetX":0,"offsetY":0,"tint":"0xffffff"},{"drawAsTexture":false,"offsetR":0,"hover":"false","allowRotation":true,"userData":"","rotation":0,"cls":"CButton","baseDim":{"y":70,"x":127},"body":null,"fontFamily":"dedgamecaps","scaleX":1.7,"scaleY":1.7,"isClip":false,"align":"center","fps":30,"id":"bstuff","autoPlay":false,"actions":[],"text":"БУСТЕРЫ","layer":3,"fontSize":"30","x":66,"y":573,"clip":"guiatlas.png.shop marker","offsetX":0,"offsetY":0,"tint":"0xffffff"},{"drawAsTexture":false,"offsetR":0,"hover":"false","allowRotation":true,"userData":"","rotation":0,"cls":"CButton","baseDim":{"y":18,"x":45.5},"body":null,"fontFamily":"","scaleX":2,"scaleY":2,"isClip":false,"align":"center","fps":30,"id":"bback","autoPlay":false,"actions":[],"text":"","layer":3,"fontSize":"","x":57.75,"y":114,"clip":"guiatlas.png.back button","offsetX":0,"offsetY":0,"tint":"0xffffff"},{"drawAsTexture":false,"offsetR":0,"hover":"true","allowRotation":true,"userData":"","rotation":0,"cls":"CButton","baseDim":{"y":19,"x":22},"body":null,"fontFamily":"dedgamecaps","scaleX":2,"scaleY":2,"isClip":false,"align":"center","fps":30,"id":"photo","autoPlay":false,"actions":[],"text":"Селфи на стену","layer":3,"fontSize":"22","x":370,"y":114.5,"clip":"guiatlas.png.photo icon","offsetX":0,"offsetY":0,"tint":"0xffffff"},{"drawAsTexture":false,"offsetR":0,"hover":"true","allowRotation":true,"userData":"","rotation":0,"cls":"CButton","baseDim":{"y":19,"x":22},"body":null,"fontFamily":"dedgamecaps","scaleX":2,"scaleY":2,"isClip":false,"align":"center","fps":30,"id":"ava","autoPlay":false,"actions":[],"text":"Селфи на аву","layer":3,"fontSize":"22","x":315,"y":116.5,"clip":"guiatlas.png.ava icon","offsetX":0,"offsetY":0,"tint":"0xffffff"},{"offsetX":0,"actions":[],"layer":1,"offsetR":0,"baseDim":{"y":196.5,"x":177.5},"allowRotation":true,"userData":"","rotation":0,"cls":"ZEngine::ZObj","clip":"guiatlas.png.ded back","x":200.75,"scaleX":3,"y":300.25,"scaleY":3,"body":null,"isClip":false,"drawAsTexture":false,"fps":30,"offsetY":0,"id":"","autoPlay":false},{"offsetX":0,"actions":[],"layer":-3,"offsetR":0,"baseDim":{"y":78.5,"x":82},"allowRotation":true,"userData":"","rotation":0,"cls":"ZEngine::ZObj","clip":"guiatlas.png.background color","x":233,"scaleX":5.853085788437705,"y":311.25,"scaleY":7.942617868031222,"body":null,"isClip":false,"drawAsTexture":false,"fps":30,"offsetY":0,"id":"bgshopded","autoPlay":false},{"drawAsTexture":false,"offsetR":0,"baseDim":{"y":32,"x":32},"allowRotation":true,"userData":"","rotation":0,"cls":"CTextField","body":null,"fontFamily":"dedgamedesc","scaleX":1,"scaleY":1,"isClip":false,"align":"center","fps":30,"id":"tfdescd","autoPlay":false,"actions":[],"text":"","layer":4,"fontSize":"18","x":207,"y":448,"clip":null,"offsetX":0,"offsetY":0,"tint":"0x111111"},{"drawAsTexture":false,"offsetR":0,"hover":"true","allowRotation":true,"userData":"","rotation":0,"cls":"CButton","baseDim":{"y":84,"x":86},"body":null,"fontFamily":"","scaleX":2,"scaleY":2,"isClip":true,"align":"center","fps":30,"id":"bboards","autoPlay":false,"actions":[],"text":"","layer":3,"fontSize":"","x":282.75,"y":524.5,"clip":"guiatlas.png.btnboard01","offsetX":0,"offsetY":0,"tint":"0xffffff"},{"drawAsTexture":false,"offsetR":0,"hover":"true","allowRotation":true,"userData":"","rotation":0,"cls":"CButton","baseDim":{"y":84,"x":86},"body":null,"fontFamily":"","scaleX":2,"scaleY":2,"isClip":true,"align":"center","fps":30,"id":"bcostumes","autoPlay":false,"actions":[],"text":"","layer":3,"fontSize":"","x":334.75,"y":512.5,"clip":"guiatlas.png.btncostume01","offsetX":0,"offsetY":0,"tint":"0xffffff"},{"drawAsTexture":false,"offsetR":0,"hover":"true","allowRotation":true,"userData":"","rotation":0,"cls":"CButton","baseDim":{"y":84,"x":86},"body":null,"fontFamily":"","scaleX":2,"scaleY":2,"isClip":true,"align":"center","fps":30,"id":"bhats","autoPlay":false,"actions":[],"text":"","layer":3,"fontSize":"","x":386.75,"y":523.5,"clip":"guiatlas.png.btnhats01","offsetX":0,"offsetY":0,"tint":"0xffffff"},{"drawAsTexture":false,"offsetR":0,"baseDim":{"y":32,"x":32},"allowRotation":true,"userData":"","rotation":0,"cls":"CTextField","body":null,"fontFamily":"dedgamecaps","scaleX":1,"scaleY":1,"isClip":false,"align":"center","fps":30,"id":"tfapp","autoPlay":false,"actions":[],"text":"","layer":3,"fontSize":"26","x":596,"y":80,"clip":null,"offsetX":0,"offsetY":0,"tint":"0xffffff"}], "layers": {"hidden":[1,-2],"locked":[-3],"names":[],"current":3,"num":[]}, "selection": [], "camera": {"y":-45.86421088737984,"zoom":1,"x":-78.91636655444313} }